CHANGELOG.rst
MANIFEST.in
README.rst
setup.py
hichao_test/__init__.py
hichao_test/conf.py
hichao_test/curl_builder.py
hichao_test/curl_reader.py
hichao_test/decorator.py
hichao_test.egg-info/PKG-INFO
hichao_test.egg-info/SOURCES.txt
hichao_test.egg-info/dependency_links.txt
hichao_test.egg-info/entry_points.txt
hichao_test.egg-info/pbr.json
hichao_test.egg-info/top_level.txt
hichao_test.egg-info/zip-safe
hichao_torn/__init__.py
hichao_torn/main.py
hichao_torn/views.py
hichao_torn/test/__init__.py
hichao_torn/test/__main__.py
hichao_torn/test/runtests.py
hichao_torn/test/test.py
hichao_torn/test/util.py