Metadata-Version: 1.1
Name: hichao-test
Version: 0.2.2
Summary: hichao-test is a Tool that HTTP Test base on linux curl.
Home-page: https://github.com/wujuguang/hichao-test.git
Author: kylinfish
Author-email: kylinfish@126.com
License: MIT License
Keywords: hichao-test
Platform: any
Classifier: Development Status :: 4 - Beta
Classifier: Environment :: Console
Classifier: Environment :: Web Environment
Classifier: Intended Audience :: Developers
Classifier: Programming Language :: Python
Classifier: Programming Language :: Python :: 2
Classifier: Programming Language :: Python :: 3
Classifier: Programming Language :: Python :: 3.4
Classifier: Topic :: Internet :: WWW/HTTP
Classifier: Topic :: Utilities
Classifier: Topic :: Software Development :: Libraries :: Python Modules
Classifier: License :: OSI Approved :: MIT License
